stack_frame_analyzer/__init__.py
stack_frame_analyzer/exceptions.py
stack_frame_analyzer/main.py
Stack_Frame_Analyzer-0.2.1.dist-info/LICENSE
Stack_Frame_Analyzer-0.2.1.dist-info/METADATA
Stack_Frame_Analyzer-0.2.1.dist-info/WHEEL
Stack_Frame_Analyzer-0.2.1.dist-info/top_level.txt
Stack_Frame_Analyzer-0.2.1.dist-info/RECORD
