Metadata-Version: 2.1
Name: Stack-Frame-Analyzer
Version: 0.2.1
Summary: It helps to get the context of a frame from the caller's stack. Can be used to improve service and microservice logs.
Home-page: https://github.com/cesarmerjan/stack_frame_analyzer
Author: Cesar Merjan
Author-email: cesarmerjan@gmail.com
License: MIT
Download-URL: https://github.com/cesarmerjan/stack_frame_analyzer/archive/refs/heads/master.zip
Keywords: logging,stack,frame
Platform: UNKNOWN
Classifier: Development Status :: 4 - Beta
Classifier: License :: OSI Approved :: Apache Software License
Classifier: Intended Audience :: Developers
Classifier: Topic :: Software Development
Classifier: Topic :: Software Development :: Bug Tracking
Classifier: Topic :: Software Development :: Debuggers
Classifier: Topic :: System :: Logging
Classifier: Topic :: System :: Software Distribution
Classifier: Topic :: Utilities
Classifier: Topic :: Software Development :: Libraries
Classifier: Programming Language :: Python :: Implementation :: CPython
Classifier: Programming Language :: Python :: 3
Classifier: Programming Language :: Python :: 3 :: Only
Classifier: Programming Language :: Python :: 3.6
Classifier: Programming Language :: Python :: 3.7
Classifier: Programming Language :: Python :: 3.8
Classifier: Operating System :: Unix
Classifier: Operating System :: MacOS :: MacOS X
Classifier: Operating System :: Microsoft :: Windows
Requires-Python: >3.6
License-File: LICENSE
